dynamarq/__init__.py
dynamarq/benchmark.py
dynamarq/clifford_dfe.py
dynamarq/benchmarks/__init__.py
dynamarq/benchmarks/algorithms/IPE.py
dynamarq/benchmarks/algorithms/PartialQFT.py
dynamarq/benchmarks/algorithms/QFT.py
dynamarq/benchmarks/algorithms/TFIM.py
dynamarq/benchmarks/eccs/FiveQubitCode.py
dynamarq/benchmarks/eccs/RepetitionCode.py
dynamarq/benchmarks/gates/CNOTLadder.py
dynamarq/benchmarks/gates/Fanout.py
dynamarq/benchmarks/gates/LongRangeCNOT.py
dynamarq/benchmarks/gates/LongRangeCNOTSparse.py
dynamarq/benchmarks/states/GHZ.py
dynamarq/benchmarks/states/GHZReset.py
dynamarq/metrics/__init__.py
dynamarq/metrics/compute_metrics.py
dynamarq-0.2.5.dist-info/licenses/LICENSE
dynamarq-0.2.5.dist-info/METADATA
dynamarq-0.2.5.dist-info/WHEEL
dynamarq-0.2.5.dist-info/top_level.txt
dynamarq-0.2.5.dist-info/RECORD
