Metadata-Version: 2.4
Name: dynamarq
Version: 0.2.5
Summary: A scalable hardware agnostic benchmarking suite for dynamic quantum circuits.
Author-email: Sumeet Shirgure <sumeetshirgure@gmail.com>
License-Expression: MIT
Project-URL: Homepage, https://github.com/sumeetshirgure/dynamarq
Project-URL: Issues, https://github.com/sumeetshirgure/dynamarq/issues
Classifier: Programming Language :: Python :: 3
Classifier: Operating System :: OS Independent
Requires-Python: >=3.10
License-File: LICENSE
Requires-Dist: qiskit
Requires-Dist: qiskit-ibm-runtime
Requires-Dist: guppylang
Requires-Dist: networkx
Dynamic: license-file
